__init__.py
cambiacosas/__main__.py
cambiacosas/administracion_archivo/__init__.py
cambiacosas/administracion_archivo/edit_file.py
cambiacosas/administracion_archivo/file_info.py
cambiacosas/googleapi/__init__.py
cambiacosas/googleapi/api_client.py
cambiacosas/googleapi/gemini_options.py
cambiacosas-0.1.2.dist-info/licenses/LICENSE
cambiacosas-0.1.2.dist-info/METADATA
cambiacosas-0.1.2.dist-info/WHEEL
cambiacosas-0.1.2.dist-info/entry_points.txt
cambiacosas-0.1.2.dist-info/top_level.txt
cambiacosas-0.1.2.dist-info/RECORD
