Metadata-Version: 2.4
Name: cambiacosas
Version: 0.1.2
Summary: Una herramienta para procesar archivos utilizando la API de Gemini, aplicando modificaciones basadas en un mensaje (prompt) proporcionado.
Author-email: Juantv01 <juanasdfg41@gmail.comm>
Maintainer-email: Juantv01 <juanasdfg41@gmail.comm>
License: MIT
Project-URL: Documentation, https://github.com/JuanJml01/CambiaCosas/tree/main/doc
Project-URL: Repository, https://github.com/JuanJml01/CambiaCosas
Keywords: gemini,api,file processing,automation,text modification
Classifier: Development Status :: 3 - Alpha
Classifier: Intended Audience :: Developers
Classifier: Topic :: Software Development :: Code Generators
Classifier: Topic :: Text Processing :: General
Classifier: Programming Language :: Python :: 3
Classifier: Programming Language :: Python :: 3.8
Classifier: Programming Language :: Python :: 3.9
Classifier: Programming Language :: Python :: 3.10
Classifier: Programming Language :: Python :: 3.11
Classifier: Programming Language :: Python :: 3.12
Classifier: License :: OSI Approved :: MIT License
Classifier: Operating System :: OS Independent
Requires-Python: >=3.8
License-File: LICENSE
Dynamic: license-file
